{
  "pensamentos": [
    {
      "id": 2,
      "conteudo": "You just wanna attention",
      "autoria": "Charlie Puth",
      "modelo": "modelo3"
    },
    {
      "id": 3,
      "conteudo": "Validando formulários",
      "autoria": "Angular",
      "modelo": "modelo2"
    },
    {
      "id": 4,
      "conteudo": "Vamos falar de nível tecnico?",
      "autoria": "Alberto Carlos",
      "modelo": "modelo2"
    },
    {
      "conteudo": "Que a força esteja contigo!",
      "autoria": "Mestre Yoda",
      "modelo": "modelo1",
      "id": 5
    },
    {
      "conteudo": "Formulário Reativo",
      "autoria": "angular",
      "modelo": "modelo3",
      "id": 6
    },
    {
      "conteudo": "Rodrick é o cara",
      "autoria": "diário de um banan",
      "modelo": "modelo1",
      "id": 7
    },
    {
      "conteudo": "PlayStation, PlayStation, PlayStation ..... Jogo da vida! ",
      "autoria": "tamashiro, yudi",
      "modelo": "modelo2",
      "id": 8
    }
  ]
}